assetbuilder.py
assetbuilder-1.0.3.dist-info/LICENSE.txt
assetbuilder-1.0.3.dist-info/METADATA
assetbuilder-1.0.3.dist-info/WHEEL
assetbuilder-1.0.3.dist-info/top_level.txt
assetbuilder-1.0.3.dist-info/RECORD
