Metadata-Version: 2.1
Name: assetbuilder
Version: 1.0.3
Summary: Build & serve your web project's asset files (JS, CSS etc)
Home-page: https://ollycope.com/software/assetbuilder/latest/
Author: Oliver Cope
Author-email: oliver@redgecko.org
License: Apache
Keywords: web,css,minify,javascript,compress,assets,wsgi,bundle
Platform: UNKNOWN
Classifier: Environment :: Web Environment
Classifier: Intended Audience :: Developers
Classifier: License :: OSI Approved :: Apache Software License
Classifier: Operating System :: OS Independent
Classifier: Programming Language :: Python :: 3
Classifier: Topic :: Internet :: WWW/HTTP :: WSGI
License-File: LICENSE.txt
Requires-Dist: portalocker
Requires-Dist: itsdangerous
